mcpup-0.1.1.dist-info/METADATA
mcpup-0.1.1.dist-info/WHEEL
mcpup-0.1.1.dist-info/entry_points.txt
mcpup-0.1.1.dist-info/licenses/LICENSE
mcpup/__init__.py
mcpup/cli.py
mcpup/generator.py
mcpup/scanner.py
mcpup/utils.py
mcpup-0.1.1.dist-info/RECORD
