Metadata-Version: 2.1
Name: mcpup
Version: 0.1.1
Summary: Generate Pydantic models for your Python package functions 🐶
Author-Email: Louis Maddox <louismmx@gmail.com>
License: MIT
Classifier: Development Status :: 4 - Beta
Classifier: Intended Audience :: Developers
Classifier: License :: OSI Approved :: MIT License
Classifier: Natural Language :: English
Classifier: Operating System :: OS Independent
Classifier: Programming Language :: Python :: 3
Classifier: Programming Language :: Python :: 3.10
Classifier: Programming Language :: Python :: 3.11
Classifier: Programming Language :: Python :: 3.12
Classifier: Programming Language :: Python :: Implementation :: CPython
Classifier: Programming Language :: Python
Project-URL: Bug Tracker, https://github.com/lmmx/mcpup/issues
Project-URL: Homepage, https://github.com/lmmx/mcpup
Requires-Python: >=3.10
Requires-Dist: pydantic>=2.0.0
Requires-Dist: pydantic-function-models>=0.1.10
Requires-Dist: click>=8.1.7
Requires-Dist: rich>=13.3.5
Provides-Extra: dev
Requires-Dist: pdm-bump>=0.9.10; extra == "dev"
Requires-Dist: pdm>=2.22.3; extra == "dev"
Requires-Dist: pre-commit>=4.1.0; extra == "dev"
Requires-Dist: pytest>=8.3.4; extra == "dev"
Provides-Extra: docs
Requires-Dist: livereload>=2.7.1; extra == "docs"
Requires-Dist: mkdocs-material[imaging,recommended]>=9.5.2; extra == "docs"
Requires-Dist: mkdocs-section-index>=0.3.8; extra == "docs"
Requires-Dist: mkdocs>=1.5.3; extra == "docs"
Requires-Dist: mkdocstrings[python]>=0.24.0; extra == "docs"
Requires-Dist: ruff>=0.9.5; extra == "docs"
Requires-Dist: urllib3<2; extra == "docs"
